peycloak/__init__.py
peycloak/api.py
peycloak/client.py
peycloak/const.py
peycloak/utils.py
peycloak-0.0.2.dist-info/METADATA
peycloak-0.0.2.dist-info/RECORD
peycloak-0.0.2.dist-info/WHEEL
peycloak-0.0.2.dist-info/top_level.txt
